CHANGES.rst
MANIFEST.in
README.rst
setup.cfg
setup.py
docs/TODO.rst
src/collective/__init__.py
src/collective.testcaselayer.egg-info/PKG-INFO
src/collective.testcaselayer.egg-info/SOURCES.txt
src/collective.testcaselayer.egg-info/dependency_links.txt
src/collective.testcaselayer.egg-info/entry_points.txt
src/collective.testcaselayer.egg-info/namespace_packages.txt
src/collective.testcaselayer.egg-info/not-zip-safe
src/collective.testcaselayer.egg-info/requires.txt
src/collective.testcaselayer.egg-info/top_level.txt
src/collective/testcaselayer/README.rst
src/collective/testcaselayer/__init__.py
src/collective/testcaselayer/common.py
src/collective/testcaselayer/common.rst
src/collective/testcaselayer/configure.zcml
src/collective/testcaselayer/ctc.py
src/collective/testcaselayer/ctc.rst
src/collective/testcaselayer/functional.py
src/collective/testcaselayer/functional.rst
src/collective/testcaselayer/layer.py
src/collective/testcaselayer/layer.rst
src/collective/testcaselayer/mail.py
src/collective/testcaselayer/mail.rst
src/collective/testcaselayer/ptc.py
src/collective/testcaselayer/ptc.rst
src/collective/testcaselayer/sandbox.py
src/collective/testcaselayer/sandbox.rst
src/collective/testcaselayer/snapshot.rst
src/collective/testcaselayer/testbrowser.py
src/collective/testcaselayer/testcase.py
src/collective/testcaselayer/testing.zcml
src/collective/testcaselayer/tests.py
src/collective/testcaselayer/ztc.py
src/collective/testcaselayer/ztc.rst
src/collective/testcaselayer/profiles/testing/componentregistry.xml
src/collective/testcaselayer/profiles/testing/toolset.xml
src/collective/testcaselayer/testing/__init__.py
src/collective/testcaselayer/testing/iterator.py
src/collective/testcaselayer/testing/layer.py
src/collective/testcaselayer/testing/loadzcml.zcml
src/collective/testcaselayer/testing/CollectiveTestCaseLayerTesting/__init__.py
src/collective/testcaselayer/testing/CollectiveTestCaseLayerTesting/Extensions/Install.py
src/collective/testcaselayer/testing/CollectiveTestCaseLayerTesting/Extensions/__init__.py