Metadata-Version: 1.1
Name: collective.testcaselayer
Version: 1.6.1
Summary: Use test cases as zope.testing layers
Home-page: http://pypi.python.org/pypi/collective.testcaselayer
Author: Ross Patterson
Author-email: me@rpatterson.net
License: GPL
Platform: UNKNOWN
Classifier: Programming Language :: Python
Classifier: Topic :: Software Development :: Libraries :: Python Modules
